MPD_sima-0.18.2.data/data/share/doc/mpd-sima/examples/album_mode.cfg
MPD_sima-0.18.2.data/data/share/doc/mpd-sima/examples/all_settings.cfg
MPD_sima-0.18.2.data/data/share/doc/mpd-sima/examples/offline_genre_plugin.cfg
MPD_sima-0.18.2.data/data/share/doc/mpd-sima/examples/offline_tags_plugin.cfg
sima/__init__.py
sima/core.py
sima/info.py
sima/launch.py
sima/mpdclient.py
sima/lib/__init__.py
sima/lib/cache.py
sima/lib/daemon.py
sima/lib/http.py
sima/lib/logger.py
sima/lib/meta.py
sima/lib/plugin.py
sima/lib/simadb.py
sima/lib/simafm.py
sima/lib/simastr.py
sima/lib/track.py
sima/lib/webserv.py
sima/plugins/__init__.py
sima/plugins/contrib/__init__.py
sima/plugins/contrib/placeholder.py
sima/plugins/core/__init__.py
sima/plugins/core/history.py
sima/plugins/core/mpdoptions.py
sima/plugins/core/uniq.py
sima/plugins/internal/__init__.py
sima/plugins/internal/crop.py
sima/plugins/internal/genre.py
sima/plugins/internal/lastfm.py
sima/plugins/internal/random.py
sima/plugins/internal/tags.py
sima/utils/__init__.py
sima/utils/blcli.py
sima/utils/config.py
sima/utils/configtest.py
sima/utils/filelock.py
sima/utils/leven.py
sima/utils/perf.py
sima/utils/startopt.py
sima/utils/utils.py
MPD_sima-0.18.2.dist-info/METADATA
MPD_sima-0.18.2.dist-info/WHEEL
MPD_sima-0.18.2.dist-info/entry_points.txt
MPD_sima-0.18.2.dist-info/top_level.txt
MPD_sima-0.18.2.dist-info/RECORD
