Metadata-Version: 2.1
Name: MPD-sima
Version: 0.18.2
Summary: Automagically add titles to MPD playlist
Home-page: https://kaliko.me/mpd-sima
Author: kaliko
Author-email: kaliko@azylum.org
License: GPLv3
Download-URL: http://media.kaliko.me/src/sima/releases/
Keywords: MPD
Platform: UNKNOWN
Classifier: Development Status :: 5 - Production/Stable
Classifier: Environment :: Console
Classifier: Environment :: No Input/Output (Daemon)
Classifier: Intended Audience :: End Users/Desktop
Classifier: License :: OSI Approved :: GNU General Public License (GPL)
Classifier: Operating System :: POSIX
Classifier: Topic :: Multimedia :: Sound/Audio
Classifier: Topic :: Utilities
Classifier: Programming Language :: Python :: 3
Classifier: Programming Language :: Python :: 3.6
Classifier: Programming Language :: Python :: 3.7
Classifier: Programming Language :: Python :: 3.8
Requires-Dist: python-musicpd (>=0.7.0)
Requires-Dist: requests (>=2.20.0)
